aep8-0.3.0.dist-info/RECORD
aep8-0.3.0.dist-info/WHEEL
aep8-0.3.0.dist-info/METADATA
aep8/__init__.py
aep8/_core.py
aep8/py.typed
aep8/_irbem.cpython-314-darwin.so
aep8/.dylibs/libgfortran.5.dylib
aep8/.dylibs/libquadmath.0.dylib
aep8/.dylibs/libgcc_s.1.1.dylib
