Metadata-Version: 2.4
Name: aep8
Version: 0.3.0
Summary: Calculate the flux of electrons or protons trapped in the Earth's radiation belt using the NASA AE8/AP8 model from IRBEM
Author-Email: Leo Singer <leo.p.singer@nasa.gov>
License-Expression: BSD-3-Clause
Classifier: Development Status :: 1 - Planning
Classifier: Operating System :: MacOS
Classifier: Operating System :: Microsoft :: Windows
Classifier: Operating System :: POSIX
Classifier: Operating System :: POSIX :: Linux
Classifier: Operating System :: Unix
Classifier: Programming Language :: Python :: 3 :: Only
Classifier: Topic :: Scientific/Engineering :: Astronomy
Classifier: Topic :: Scientific/Engineering :: Physics
Classifier: Typing :: Typed
Project-URL: GitHub, https://github.com/m4opt/aep8
Requires-Python: >=3.11
Requires-Dist: astropy
Provides-Extra: test
Requires-Dist: pytest; extra == "test"
Requires-Dist: pytest-mpl; extra == "test"
